{
  "main": {
    "id": "0575f63b7890a684",
    "type": "split",
    "children": [
      {
        "id": "6d24292b1bd8d8aa",
        "type": "tabs",
        "children": [
          {
            "id": "a79dfd0451cc095e",
            "type": "leaf",
            "state": {
              "type": "canvas",
              "state": {
                "file": "1-semestre/Canvas/CS - Fluxo Disciplina.canvas",
                "viewState": {
                  "x": 76,
                  "y": -381.6000061035156,
                  "zoom": 0
                }
              },
              "icon": "lucide-layout-dashboard",
              "title": "CS - Fluxo Disciplina"
            }
          },
          {
            "id": "9d315179d3907361",
            "type": "leaf",
            "state": {
              "type": "canvas",
              "state": {
                "file": "1-semestre/Canvas/CS - Fluxo Disciplina.canvas",
                "viewState": {
                  "x": 123.45769672142319,
                  "y": -614.2361063062094,
                  "zoom": 0.15345120731284634
                }
              },
              "icon": "lucide-layout-dashboard",
              "title": "CS - Fluxo Disciplina"
            }
          },
          {
            "id": "756ba6a80ddedabe",
            "type": "leaf",
            "state": {
              "type": "markdown",
              "state": {
                "file": "Datas Provas.md",
                "mode": "source",
                "source": false
              },
              "icon": "lucide-file",
              "title": "Datas Provas"
            }
          },
          {
            "id": "266c912e7d5f8000",
            "type": "leaf",
            "state": {
              "type": "markdown",
              "state": {
                "file": "1-semestre/Data_provas/2024-10-04 Prova 01 - IP.md",
                "mode": "source",
                "source": false
              },
              "icon": "lucide-file",
              "title": "2024-10-04 Prova 01 - IP"
            }
          },
          {
            "id": "6e27a7b6415e4a46",
            "type": "leaf",
            "state": {
              "type": "full-calendar-view",
              "state": {},
              "icon": "calendar-glyph",
              "title": "Calendar"
            }
          },
          {
            "id": "f17598992457ea31",
            "type": "leaf",
            "state": {
              "type": "canvas",
              "state": {
                "file": "1-semestre/Canvas/IP - Fluxo_Disciplina.canvas",
                "viewState": {
                  "x": -98,
                  "y": 800,
                  "zoom": -0.4061750371108248
                }
              },
              "icon": "lucide-layout-dashboard",
              "title": "IP - Fluxo_Disciplina"
            }
          },
          {
            "id": "be1a5768ea138caa",
            "type": "leaf",
            "state": {
              "type": "pdf",
              "state": {
                "file": "1-semestre/CS/Plano_Ensino.pdf"
              },
              "icon": "lucide-file-text",
              "title": "Plano_Ensino"
            }
          },
          {
            "id": "259af191fd3c6044",
            "type": "leaf",
            "state": {
              "type": "pdf",
              "state": {
                "file": "Pesquisa_UFG/LIVRO-Revisao Sistematica da Literatura em Engenharia de Software_ Teoria e Pratica - Elisa Yumi Nakagawa.pdf"
              },
              "icon": "lucide-file-text",
              "title": "LIVRO-Revisao Sistematica da Literatura em Engenharia de Software_ Teoria e Pratica - Elisa Yumi Nakagawa"
            }
          },
          {
            "id": "3db424e5e5531543",
            "type": "leaf",
            "state": {
              "type": "markdown",
              "state": {
                "file": "Accessibility Guidelines for VR Games - A Comparison and Synthesis of a Comprehensive Set.md",
                "mode": "source",
                "source": false
              },
              "icon": "lucide-file",
              "title": "Accessibility Guidelines for VR Games - A Comparison and Synthesis of a Comprehensive Set"
            }
          },
          {
            "id": "2abf8c6c6b17b75e",
            "type": "leaf",
            "state": {
              "type": "markdown",
              "state": {
                "file": "2024-11-04.md",
                "mode": "source",
                "source": false
              },
              "icon": "lucide-file",
              "title": "2024-11-04"
            }
          },
          {
            "id": "1269ebeb416a8a03",
            "type": "leaf",
            "state": {
              "type": "release-notes",
              "state": {
                "currentVersion": "1.7.5"
              },
              "icon": "lucide-file",
              "title": "Release Notes 1.7.5"
            }
          },
          {
            "id": "03208700cc14d0de",
            "type": "leaf",
            "state": {
              "type": "markdown",
              "state": {
                "file": "Pesquisa_UFG/Resumo Revisão Sistemática.md",
                "mode": "source",
                "source": false
              },
              "icon": "lucide-file",
              "title": "Resumo Revisão Sistemática"
            }
          },
          {
            "id": "e8f70dd408840224",
            "type": "leaf",
            "state": {
              "type": "markdown",
              "state": {
                "file": "Pesquisa_UFG/Resumo Revisão Sistemática.md",
                "mode": "source",
                "source": false
              },
              "icon": "lucide-file",
              "title": "Resumo Revisão Sistemática"
            }
          },
          {
            "id": "a48c5e154987a097",
            "type": "leaf",
            "state": {
              "type": "pdf",
              "state": {
                "file": "Pesquisa_UFG/LIVRO-Revisao Sistematica da Literatura em Engenharia de Software_ Teoria e Pratica - Elisa Yumi Nakagawa.pdf"
              },
              "icon": "lucide-file-text",
              "title": "LIVRO-Revisao Sistematica da Literatura em Engenharia de Software_ Teoria e Pratica - Elisa Yumi Nakagawa"
            }
          }
        ],
        "currentTab": 13
      }
    ],
    "direction": "vertical"
  },
  "left": {
    "id": "805a03dd317fd7d9",
    "type": "split",
    "children": [
      {
        "id": "87cc29eac8e81d83",
        "type": "tabs",
        "children": [
          {
            "id": "34bd9282353c50cb",
            "type": "leaf",
            "state": {
              "type": "file-explorer",
              "state": {
                "sortOrder": "alphabetical"
              },
              "icon": "lucide-folder-closed",
              "title": "Files"
            }
          },
          {
            "id": "f481b86763966747",
            "type": "leaf",
            "state": {
              "type": "search",
              "state": {
                "query": "",
                "matchingCase": false,
                "explainSearch": false,
                "collapseAll": false,
                "extraContext": false,
                "sortOrder": "alphabetical"
              },
              "icon": "lucide-search",
              "title": "Search"
            }
          },
          {
            "id": "c1dbc52c90c36460",
            "type": "leaf",
            "state": {
              "type": "bookmarks",
              "state": {},
              "icon": "lucide-bookmark",
              "title": "Bookmarks"
            }
          }
        ]
      }
    ],
    "direction": "horizontal",
    "width": 200
  },
  "right": {
    "id": "c67936717c7f0a80",
    "type": "split",
    "children": [
      {
        "id": "a52be26b54d2ed59",
        "type": "tabs",
        "children": [
          {
            "id": "aea745c6e7511690",
            "type": "leaf",
            "state": {
              "type": "backlink",
              "state": {
                "file": "Pesquisa_UFG/Resumo Revisão Sistemática.md",
                "collapseAll": false,
                "extraContext": false,
                "sortOrder": "alphabetical",
                "showSearch": false,
                "searchQuery": "",
                "backlinkCollapsed": false,
                "unlinkedCollapsed": true
              },
              "icon": "links-coming-in",
              "title": "Backlinks for Resumo Revisão Sistemática"
            }
          },
          {
            "id": "68d04117329e59d2",
            "type": "leaf",
            "state": {
              "type": "outgoing-link",
              "state": {
                "file": "Pesquisa_UFG/Resumo Revisão Sistemática.md",
                "linksCollapsed": false,
                "unlinkedCollapsed": true
              },
              "icon": "links-going-out",
              "title": "Outgoing links from Resumo Revisão Sistemática"
            }
          },
          {
            "id": "f2f6111bddcc4e5b",
            "type": "leaf",
            "state": {
              "type": "tag",
              "state": {
                "sortOrder": "frequency",
                "useHierarchy": true
              },
              "icon": "lucide-tags",
              "title": "Tags"
            }
          },
          {
            "id": "f352bd1b3692460f",
            "type": "leaf",
            "state": {
              "type": "outline",
              "state": {
                "file": "Pesquisa_UFG/Resumo Revisão Sistemática.md"
              },
              "icon": "lucide-list",
              "title": "Outline of Resumo Revisão Sistemática"
            }
          }
        ],
        "currentTab": 3
      }
    ],
    "direction": "horizontal",
    "width": 200,
    "collapsed": true
  },
  "left-ribbon": {
    "hiddenItems": {
      "switcher:Open quick switcher": false,
      "graph:Open graph view": false,
      "canvas:Create new canvas": false,
      "daily-notes:Open today's daily note": false,
      "templates:Insert template": false,
      "command-palette:Open command palette": false,
      "obsidian-full-calendar:Open Full Calendar": false,
      "completed-task-display:Task Hider": false
    }
  },
  "active": "a48c5e154987a097",
  "lastOpenFiles": [
    "Pesquisa_UFG/01 - O que é RS.md",
    "Pesquisa_UFG/Resumo Revisão Sistemática.md",
    "Untitled",
    "Etarismo.md",
    "2024-11-04.md",
    "Accessibility Guidelines for VR Games - A Comparison and Synthesis of a Comprehensive Set.md",
    "Pesquisa_UFG/LIVRO-Revisao Sistematica da Literatura em Engenharia de Software_ Teoria e Pratica - Elisa Yumi Nakagawa.pdf",
    "Pesquisa_UFG/frvir-02-697504.pdf",
    "Pesquisa_UFG/frvir-02-697504.pdf.crdownload",
    "Datas Provas.md",
    "Pesquisa_UFG/LIVRO-Revisao Sistematica da Literatura em Engenharia de Software_ Teoria e Pratica - Elisa Yumi Nakagawa.pdf.crdownload",
    "Pesquisa_UFG",
    "Nova pasta",
    "1-semestre/Data_provas/2024-10-04 Prova 01 - IP.md",
    "1-semestre/Data_provas/2024-12-17 Prova 03 - IP.md",
    "1-semestre/Data_provas",
    "1-semestre/Data_provas/2024-12-12 Prova U - CS.md",
    "1-semestre/Data_provas/2024-12-16 Prova 02 - FMC.md",
    "1-semestre/Data_provas/2024-10-21 Prova 01 - FMC.md",
    "1-semestre/Data_provas/2024-12-05 Prova 02 - GA.md",
    "1-semestre/Data_provas/2024-10-17 Prova 01 - GA.md",
    "1-semestre/Data_provas/2024-11-22 Prova 02 - IP.md",
    "1-semestre/CS/Plano_Ensino.pdf",
    "1-semestre/IP/Plano_Ensino_IP.pdf",
    "2024-09-23.md",
    "1-semestre/Canvas/CS - Fluxo Disciplina.canvas",
    "1-semestre/CS/Computação e Sociedade 2024-2.md",
    "1-semestre/Canvas/IP - Fluxo_Disciplina.canvas",
    "1-semestre/IP/codigos/Lista_01_Vinicius/Lista_01_Vinicius 1.md",
    "1-semestre/IP/codigos/Lista_01_Vinicius/Lista_01_Vinicius.md"
  ]
}